{"author-retrieval-response": [{"@status": "found", "@_fa": "true", "coredata":{"prism:url":"http://api.elsevier.com/content/author/author_id/57650756800","dc:identifier":"AUTHOR_ID:57650756800","historical-identifier": [{"@_fa": "true", "$" :"author_id:57988319500"}],"eid":"9-s2.0-57650756800","document-count":"10","cited-by-count":"55","citation-count":"63","link": [{"@href": "https://www.scopus.com/authid/detail.uri?partnerID=HzOxMe3b&authorId=57650756800&origin=inward", "@rel": "scopus-author", "@_fa": "true"},{"@href": "http://api.elsevier.com/content/author/author_id/57650756800", "@rel": "self", "@_fa": "true"},{"@href": "http://api.elsevier.com/content/search/scopus?query=au-id%2857650756800%29", "@rel": "search", "@_fa": "true"},{"@href": "http://api.elsevier.com/content/search/author?co-author=57650756800", "@rel": "coauthor-search", "@_fa": "true"}]},"h-index":"4","coauthor-count":"12","affiliation-current":{"@id": "60009647", "@href": "http://api.elsevier.com/content/affiliation/affiliation_id/60009647"},"affiliation-history":{"affiliation": [{"@_fa": "true", "@id": "60009647", "@href": "http://api.elsevier.com/content/affiliation/affiliation_id/60009647"},{"@_fa": "true", "@id": "60250855", "@href": "http://api.elsevier.com/content/affiliation/affiliation_id/60250855"},{"@_fa": "true", "@id": "60105477", "@href": "http://api.elsevier.com/content/affiliation/affiliation_id/60105477"},{"@_fa": "true", "@id": "60123796", "@href": "http://api.elsevier.com/content/affiliation/affiliation_id/60123796"},{"@_fa": "true", "@id": "60106017", "@href": "http://api.elsevier.com/content/affiliation/affiliation_id/60106017"},{"@_fa": "true", "@id": "60007136", "@href": "http://api.elsevier.com/content/affiliation/affiliation_id/60007136"},{"@_fa": "true", "@id": "60008134", "@href": "http://api.elsevier.com/content/affiliation/affiliation_id/60008134"}]},"subject-areas":{"subject-area": [{"@_fa": "true", "@abbrev": "COMP", "@code": "1703", "$" :"Computational Theory and Mathematics"},{"@_fa": "true", "@abbrev": "COMP", "@code": "1711", "$" :"Signal Processing"},{"@_fa": "true", "@abbrev": "COMP", "@code": "1712", "$" :"Software"},{"@_fa": "true", "@abbrev": "COMP", "@code": "1701", "$" :"Computer Science (miscellaneous)"},{"@_fa": "true", "@abbrev": "COMP", "@code": "1707", "$" :"Computer Vision and Pattern Recognition"},{"@_fa": "true", "@abbrev": "ENGI", "@code": "2214", "$" :"Media Technology"},{"@_fa": "true", "@abbrev": "PHYS", "@code": "3102", "$" :"Acoustics and Ultrasonics"},{"@_fa": "true", "@abbrev": "MATH", "@code": "2605", "$" :"Computational Mathematics"},{"@_fa": "true", "@abbrev": "COMP", "@code": "1706", "$" :"Computer Science Applications"},{"@_fa": "true", "@abbrev": "ENGI", "@code": "2213", "$" :"Safety, Risk, Reliability and Quality"},{"@_fa": "true", "@abbrev": "ENGI", "@code": "2208", "$" :"Electrical and Electronic Engineering"},{"@_fa": "true", "@abbrev": "COMP", "@code": "1710", "$" :"Information Systems"},{"@_fa": "true", "@abbrev": "ENGI", "@code": "2207", "$" :"Control and Systems Engineering"}]},"author-profile":{"status":"update","date-created":{"@year": "2022", "@month": "05", "@day": "09"},"alias":{"@current-status": "moved-from", "aliased-id":{"@status": "moved-from", "@timestamp": "2023-07-03T21:59:43.000043-04:00", "$" :"57988319500"}},"preferred-name":{"@source": "internal-ani", "initials":"F.","indexed-name":"Feng F.","surname":"Feng","given-name":"Fangchen"},"classificationgroup":{"classifications":{"@type": "ASJC", "classification": [{"@frequency": "1", "$" :"1703"},{"@frequency": "9", "$" :"1711"},{"@frequency": "3", "$" :"1712"},{"@frequency": "1", "$" :"1701"},{"@frequency": "2", "$" :"1707"},{"@frequency": "3", "$" :"2214"},{"@frequency": "1", "$" :"3102"},{"@frequency": "1", "$" :"2605"},{"@frequency": "1", "$" :"1706"},{"@frequency": "1", "$" :"2213"},{"@frequency": "6", "$" :"2208"},{"@frequency": "1", "$" :"1710"},{"@frequency": "1", "$" :"2207"}]}},"publication-range":{"@start": "2014", "@end": "2022"},"affiliation-current":{"affiliation":{"@affiliation-id": "60009647", "@source": "internal-ani", "ip-doc":{"@id": "60009647", "@type": "parent", "@relationship": "author", "afnameid":"University Sorbonne Paris Nord#60009647","afdispname":"University Sorbonne Paris Nord","manual-curation":{"@curated": "true", "date-curation":{"@day": "22", "@month": "09", "@timestamp": "2020-09-22T09:08:03.471-04:00", "@year": "2020"},"curation-source":"PARITY","curation-type":"PARITY-22092020060803414"},"preferred-name":{"@date-locked": "2020-09-22T09:48:45.030-04:00", "@source": "corrapi-external", "$" :"University Sorbonne Paris Nord"},"sort-name":"Sorbonne Paris Nord, University","address":{"@country": "fra", "address-part":"99, av. Jean-Baptiste Clément","city":"Villetaneuse","state":"Ile-de-France","postal-code":"93430","country":"France"},"org-domain":"univ-paris13.fr","org-URL":"https://www.univ-paris13.fr/en/"}}},"affiliation-history":{"affiliation": [{"@affiliation-id": "60009647", "@source": "internal-ani", "ip-doc":{"@id": "60009647", "@type": "parent", "@relationship": "author", "afnameid":"University Sorbonne Paris Nord#60009647","afdispname":"University Sorbonne Paris Nord","manual-curation":{"@curated": "true", "date-curation":{"@day": "22", "@month": "09", "@timestamp": "2020-09-22T09:08:03.471-04:00", "@year": "2020"},"curation-source":"PARITY","curation-type":"PARITY-22092020060803414"},"preferred-name":{"@date-locked": "2020-09-22T09:48:45.030-04:00", "@source": "corrapi-external", "$" :"University Sorbonne Paris Nord"},"sort-name":"Sorbonne Paris Nord, University","address":{"@country": "fra", "address-part":"99, av. Jean-Baptiste Clément","city":"Villetaneuse","state":"Ile-de-France","postal-code":"93430","country":"France"},"org-domain":"univ-paris13.fr","org-URL":"https://www.univ-paris13.fr/en/"}},{"@affiliation-id": "60250855", "@source": "internal-ani", "ip-doc":{"@id": "60250855", "@type": "parent", "@relationship": "author", "afnameid":"Laboratoire de Traitement et Transport de l'Information (L2TI)#60250855","afdispname":"Laboratoire de Traitement et Transport de l'Information (L2TI)","preferred-name":{"@source": "internal-ani", "$" :"Laboratoire de Traitement et Transport de l'Information (L2TI)"},"sort-name":"Information Processing and Transport Laboratory","address":{"@country": "fra", "address-part":"Institut Galilée – Université Sorbonne Paris Nord, 99, avenue Jean-Baptiste Clément","city":"Villetaneuse","state":"Ile-de-France","postal-code":"93430","country":"France"},"org-domain":"l2ti.univ-paris13.fr","org-URL":"https://www-l2ti.univ-paris13.fr/"}},{"@affiliation-id": "60105477", "@source": "internal-ani", "ip-doc":{"@id": "60105477", "@type": "parent", "@relationship": "author", "afnameid":"APC - AstroParticule et Cosmologie#60105477","afdispname":"APC - AstroParticule et Cosmologie","manual-curation":{"@curated": "true", "date-curation":{"@day": "26", "@month": "03", "@timestamp": "2016-03-26T13:41:35.016-04:00", "@year": "2016"},"curation-source":"QABOAPI","curation-type":"QABO-2088067"},"preferred-name":{"@source": "internal-ani", "$" :"APC - AstroParticule et Cosmologie"},"sort-name":"AstroParticle and Cosmology (APC) Laboratory","address":{"@country": "fra", "address-part":"Université de Paris, Campus des Grands Moulins, Bâtiment Condorcet, 10, rue Alice Domon et Léonie Duquet","city":"Paris","state":"Ile-de-France","postal-code":"75013","country":"France"},"org-domain":"apc.univ-paris7.fr","org-URL":"http://www.apc.univ-paris7.fr/APC_CS/fr"}},{"@affiliation-id": "60123796", "@source": "internal-ani", "ip-doc":{"@id": "60123796", "@type": "parent", "@relationship": "author", "afnameid":"Université Paris Cité#60123796","afdispname":"Université Paris Cité","preferred-name":{"@source": "internal-ani", "$" :"Université Paris Cité"},"sort-name":"Paris, University of","address":{"@country": "fra", "address-part":"85 boulevard Saint-Germain","city":"Paris","state":"Ile-de-France","postal-code":"75006","country":"France"},"org-domain":"u-paris.fr","org-URL":"https://u-paris.fr/"}},{"@affiliation-id": "60106017", "@source": "internal-ani", "ip-doc":{"@id": "60106017", "@type": "parent", "@relationship": "author", "afnameid":"Université Paris-Saclay#60106017","afdispname":"Université Paris-Saclay","manual-curation":{"@curated": "true", "date-curation":{"@day": "07", "@month": "09", "@timestamp": "2022-09-07T01:30:16.150-04:00", "@year": "2022"},"curation-source":"Elsevier","curation-type":"SCOPUS-4135073"},"preferred-name":{"@source": "internal-ani", "$" :"Université Paris-Saclay"},"sort-name":"Paris-Saclay University","address":{"@country": "fra", "address-part":"Bâtiment Bréguet, 3 rue Joliot Curie","city":"Gif-sur-Yvette","state":"Ile-de-France","postal-code":"91190","country":"France"},"org-domain":"universite-paris-saclay.fr","org-URL":"https://www.universite-paris-saclay.fr/fr"}},{"@affiliation-id": "60007136", "@source": "internal-ani", "ip-doc":{"@id": "60007136", "@type": "parent", "@relationship": "author", "afnameid":"Laboratoire des Signaux et Systèmes#60007136","afdispname":"Laboratoire des Signaux et Systèmes","preferred-name":{"@source": "internal-ani", "$" :"Laboratoire des Signaux et Systèmes"},"sort-name":"Laboratory of Signals and Systems","address":{"@country": "fra", "address-part":"Université Paris-Saclay, CNRS, CentraleSupélec (Bat. Bréguet), 3, Rue Joliot-Curie","city":"Gif-sur-Yvette","state":"Ile-de-France","postal-code":"91192, cedex","country":"France"},"org-domain":"l2s.centralesupelec.fr","org-URL":"http://l2s.centralesupelec.fr/"}},{"@affiliation-id": "60008134", "@source": "internal-ani", "ip-doc":{"@id": "60008134", "@type": "parent", "@relationship": "author", "afnameid":"CNRS Centre National de la Recherche Scientifique#60008134","afdispname":"CNRS Centre National de la Recherche Scientifique","preferred-name":{"@source": "internal-ani", "$" :"CNRS Centre National de la Recherche Scientifique"},"sort-name":"CNRS National Centre for Scientific Research","address":{"@country": "fra", "address-part":"3 rue Michel-Ange","city":"Paris","postal-code":"75794","country":"France"},"org-domain":"cnrs.fr","org-URL":"https://www.cnrs.fr/en"}}]}}}]}